logo.py
logo_demo.py
french_logo-0.1.1.dist-info/METADATA
french_logo-0.1.1.dist-info/WHEEL
french_logo-0.1.1.dist-info/top_level.txt
french_logo-0.1.1.dist-info/RECORD
