Metadata-Version: 2.1
Name: french-logo
Version: 0.1.1
Summary: french-logo: La classe Tortue retourne une émulation de logo, basée sur le module turtle et en français
Home-page: https://framagit.org/zenjo/timetime/wikis/home
Author: Robert Sebille
Author-email: robert@sebille.name
Maintainer: Robert Sebille
Maintainer-email: robert@sebille.name
License: GNU GPL
Download-URL: https://framagit.org/zenjo/timetime/tree/master
Keywords: logo turtle pédagogique enseignement development
Platform: UNKNOWN
Classifier: Programming Language :: Python :: 3
Classifier: License :: OSI Approved :: GNU General Public License (GPL)
Classifier: Operating System :: OS Independent
